{"preguntas": [{"tema": "9", "numero": "1", "enunciado": "Una crisis econ\u00f3mica que crea una contracci\u00f3n en el Mercado de una empresa es una:", "0": "Debilidad", "1": "Amenaza", "correcto": "1", "2": "Fortaleza", "3": "Oportunidad"}, {"tema": "9", "numero": "2", "enunciado": "La empresa se enfrenta a amenazas externas sin las fortalezas internas necesarias para luchar contra la competencia de adoptar una estrategia:", "0": "Defensiva", "1": "Ofensiva", "2": "De Supervivencia", "correcto": "2", "3": "De Reorientaci\u00f3n"}, {"tema": "9", "numero": "3", "enunciado": "Un producto que ha alcanzado sus m\u00e1ximas ventas en los \u00faltimos a\u00f1os est\u00e1 en fase:", "0": "Emergente", "1": "Crecimiento", "2": "Madurez", "correcto": "2", "3": "Declive"}, {"tema": "9", "numero": "4", "enunciado": "Si el V.A.N. de una inversi\u00f3n de 500.000 \u20ac empresa para un tipo de inter\u00e9s esperado del 15% a 5 a\u00f1os es de 3.000\u20ac, entonces:", "0": "El TIR > 15", "correcto": "0", "1": "El TIR < 15", "2": "El Pay Back es de 5 a\u00f1os", "3": "El TIR = 15"}, {"tema": "9", "numero": "5", "enunciado": "El PAY BACK se alcanza cuando:", "0": "Cuando el TIR es cero", "1": "Cuando se cumplen el a\u00f1o en que el VAN es cero para un tipo de inter\u00e9s del 10%", "2": "Cuando se cumplen el a\u00f1o en que el VAN es cero para un tipo de inter\u00e9s del 0%", "correcto": "2", "3": "En ninguno de los casos anteriores"}, {"tema": "9", "numero": "6", "enunciado": "Para una empresa de fabricaci\u00f3n de chupetes, el incremento de la poblaci\u00f3n inmigante joven supondr\u00eda en un an\u00e1liss DAFO una:", "0": "Debilidad", "1": "Amenaza", "2": "Fortaleza", "3": "Oportunidad", "correcto": "2"}, {"tema": "9", "numero": "7", "enunciado": "Para una inversi\u00f3n a cinco a\u00f1os, si su TIR = 10 %, su Pay Back es:", "0": "Mayor de 5 %", "1": "Mayor del 10 %", "2": "Menor de 5 a\u00f1os", "correcto": "2", "3": "Igual a 5 a\u00f1os"}, {"tema": "9", "numero": "8", "enunciado": "Una buena imagen de marca supondr\u00eda en un an\u00e1liss DAFO una:", "0": "Debilidad", "1": "Amenaza", "2": "Fortaleza", "correcto": "2", "3": "Oportunidad"}]}